{
  "dependencies": [
    "1060064624553EF9"
  ],
  "tasks": {
    "2964F376BBEBED22": {
      "type": "heracles:item",
      "item": "minecraft:leather",
      "amount": 4,
      "collection": "AUTOMATIC",
      "title": "",
      "icon": {
        "item": {
          "id": "minecraft:air",
          "count": 0
        },
        "type": "heracles:item"
      }
    }
  },
  "rewards": {},
  "display": {
    "subtitle": {
      "translate": "Obtain 4x Leather."
    },
    "description": [
      "<subtitle id=\"6760E7AE17D1132F\" bold=\"true\" centered=\"true\" color=\"lightgray\"/>",
      "<hr/>",
      "<task task=\"2964F376BBEBED22\" quest=\"6760E7AE17D1132F\"/>",
      "<hr/>"
    ],
    "groups": {
      "Backpacks": {
        "position": [
          80,
          -32
        ]
      }
    },
    "icon": {
      "item": {
        "id": "minecraft:leather",
        "count": 1
      },
      "type": "heracles:item"
    },
    "icon_background": "heracles:textures/gui/quest_backgrounds/default.png",
    "title": {
      "translate": "Leather"
    }
  },
  "settings": {
    "unlockNotification": false,
    "showDependencyArrow": true,
    "repeatable": false,
    "individual_progress": false,
    "hidden": "LOCKED"
  }
}